mag_safe_finder/__init__.py
mag_safe_finder/main.py
mag_safe_finder/prompts.py
mag_safe_finder-2025.12.21232119.dist-info/METADATA
mag_safe_finder-2025.12.21232119.dist-info/WHEEL
mag_safe_finder-2025.12.21232119.dist-info/top_level.txt
mag_safe_finder-2025.12.21232119.dist-info/RECORD
