Metadata-Version: 2.4
Name: mag-safe-finder
Version: 2025.12.21232119
Summary: mag-safe-finder recommends the perfect MagSafe cable based on your inputs, highlighting compatibility, pros/cons, and care tips.
Author-email: mag-safe-finder <hi@eugene.plus>
License: MIT
Project-URL: Homepage, https://github.com/chigwell/mag-safe-finder
Requires-Python: >=3.9
Requires-Dist: langchain-llm7>=0.0.0
Requires-Dist: llmatch-messages>=0.0.0
Requires-Dist: langchain-core>=0.3.0
